mkdocs_markmap/__init__.py
mkdocs_markmap/__meta__.py
mkdocs_markmap/defaults.py
mkdocs_markmap/extension.py
mkdocs_markmap/plugin.py
mkdocs_markmap/utils.py
mkdocs_markmap/static_files/mkdocs-markmap.css
mkdocs_markmap/static_files/mkdocs-markmap.js
mkdocs_markmap-2.5.0.dist-info/LICENSE
mkdocs_markmap-2.5.0.dist-info/METADATA
mkdocs_markmap-2.5.0.dist-info/WHEEL
mkdocs_markmap-2.5.0.dist-info/entry_points.txt
mkdocs_markmap-2.5.0.dist-info/top_level.txt
mkdocs_markmap-2.5.0.dist-info/RECORD
