Metadata-Version: 2.1
Name: mkdocs-markmap
Version: 2.5.0
Summary: MkDocs plugin and extension to creates mindmaps from markdown using markmap
Home-page: https://github.com/markmap/mkdocs-markmap
Author: neatc0der
Author-email: 
License: MIT
Keywords: mkdocs python markdown markmap mindmap include
Platform: UNKNOWN
Classifier: Development Status :: 5 - Production/Stable
Classifier: Intended Audience :: Developers
Classifier: Intended Audience :: Information Technology
Classifier: License :: OSI Approved :: MIT License
Classifier: Programming Language :: Python :: 3
Classifier: Programming Language :: Python :: 3.7
Classifier: Programming Language :: Python :: 3.8
Classifier: Programming Language :: Python :: 3.9
Classifier: Programming Language :: Python :: 3.10
Requires-Python: >=3.7
License-File: LICENSE
Requires-Dist: mkdocs<2,>=1.3
Requires-Dist: attrs>=20.3.0
Requires-Dist: beautifulsoup4>=4.6.3
Requires-Dist: requests<3
